progpysmt/__init__.py
progpysmt/__main__.py
progpysmt/cmd/__init__.py
progpysmt/cmd/check_version.py
progpysmt/cmd/install.py
progpysmt/cmd/installers/__init__.py
progpysmt/cmd/installers/base.py
progpysmt/cmd/installers/bdd.py
progpysmt/cmd/installers/btor.py
progpysmt/cmd/installers/cvc4.py
progpysmt/cmd/installers/msat.py
progpysmt/cmd/installers/pico.py
progpysmt/cmd/installers/yices.py
progpysmt/cmd/installers/z3.py
progpysmt/cmd/shell.py
progpysmt/configuration.py
progpysmt/constants.py
progpysmt/decorators.py
progpysmt/environment.py
progpysmt/exceptions.py
progpysmt/factory.py
progpysmt/fnode.py
progpysmt/formula.py
progpysmt/logics.py
progpysmt/operators.py
progpysmt/oracles.py
progpysmt/parsing.py
progpysmt/ppsmttyping.py
progpysmt/printers.py
progpysmt/pslobject.py
progpysmt/rewritings.py
progpysmt/shortcuts.py
progpysmt/simplifier.py
progpysmt/smtlib/__init__.py
progpysmt/smtlib/annotations.py
progpysmt/smtlib/commands.py
progpysmt/smtlib/parser/__init__.py
progpysmt/smtlib/parser/parser.py
progpysmt/smtlib/printers.py
progpysmt/smtlib/script.py
progpysmt/smtlib/solver.py
progpysmt/smtlib/utils.py
progpysmt/solvers/__init__.py
progpysmt/solvers/bdd.py
progpysmt/solvers/btor.py
progpysmt/solvers/cvc4.py
progpysmt/solvers/eager.py
progpysmt/solvers/interpolation.py
progpysmt/solvers/msat.py
progpysmt/solvers/options.py
progpysmt/solvers/pico.py
progpysmt/solvers/portfolio.py
progpysmt/solvers/qelim.py
progpysmt/solvers/smtlib.py
progpysmt/solvers/solver.py
progpysmt/solvers/yices.py
progpysmt/solvers/z3.py
progpysmt/substituter.py
progpysmt/test/__init__.py
progpysmt/test/examples.py
progpysmt/test/smtlib/__init__.py
progpysmt/test/smtlib/parser_utils.py
progpysmt/test/smtlib/test_annotations.py
progpysmt/test/smtlib/test_fuzzed.py
progpysmt/test/smtlib/test_generic_wrapper.py
progpysmt/test/smtlib/test_griggio.py
progpysmt/test/smtlib/test_model_validation.py
progpysmt/test/smtlib/test_parser_examples.py
progpysmt/test/smtlib/test_parser_extensibility.py
progpysmt-0.1.2.dist-info/WHEEL
progpysmt-0.1.2.dist-info/METADATA
progpysmt-0.1.2.dist-info/RECORD
