Metadata-Version: 2.1
Name: progpysmt
Version: 0.1.2
Summary: A Python parser for SMT-LIB, SyGuS and ProgSynth formats.
License: MIT
Author: Gaëtan MARGUERITTE
Author-email: gamargueritte@gmail.com
Requires-Python: >=3.6,<4.0
Classifier: License :: OSI Approved :: MIT License
Classifier: Programming Language :: Python :: 3
Classifier: Programming Language :: Python :: 3.6
Classifier: Programming Language :: Python :: 3.7
Classifier: Programming Language :: Python :: 3.8
Classifier: Programming Language :: Python :: 3.9
Classifier: Programming Language :: Python :: 3.10
Classifier: Programming Language :: Python :: 3.11
Requires-Dist: cython (>=3.0.8,<4.0.0)
